object_by_name.py
setup.py
object_by_name.egg-info/PKG-INFO
object_by_name.egg-info/SOURCES.txt
object_by_name.egg-info/dependency_links.txt
object_by_name.egg-info/top_level.txt