Metadata-Version: 1.1
Name: object-by-name
Version: 0.0.1
Summary: Get an object by name or dotted path, import if it necessary.
Home-page: https://github.com/imbolc/object_by_name
Author: Imbolc
Author-email: imbolc@imbolc.name
License: ISC
Platform: UNKNOWN
Classifier: Development Status :: 4 - Beta
Classifier: Intended Audience :: Developers
Classifier: License :: OSI Approved :: ISC License (ISCL)
Classifier: Programming Language :: Python
Classifier: Programming Language :: Python :: 3
